{
  "formatVersion": 1,
  "database": {
    "version": 1,
    "identityHash": "593585992d558d718977027a4312716a",
    "entities": [
      {
        "tableName": "cached_user_profile",
        "createSql": "CREATE TABLE IF NOT EXISTS `${TABLE_NAME}` (`id` TEXT NOT NULL, `fullName` TEXT, `phone` TEXT, `email` TEXT, `avatarUrl` TEXT, `role` TEXT, `cachedAt` INTEGER NOT NULL, PRIMARY KEY(`id`))",
        "fields": [
          {
            "fieldPath": "id",
            "columnName": "id",
            "affinity": "TEXT",
            "notNull": true
          },
          {
            "fieldPath": "fullName",
            "columnName": "fullName",
            "affinity": "TEXT",
            "notNull": false
          },
          {
            "fieldPath": "phone",
            "columnName": "phone",
            "affinity": "TEXT",
            "notNull": false
          },
          {
            "fieldPath": "email",
            "columnName": "email",
            "affinity": "TEXT",
            "notNull": false
          },
          {
            "fieldPath": "avatarUrl",
            "columnName": "avatarUrl",
            "affinity": "TEXT",
            "notNull": false
          },
          {
            "fieldPath": "role",
            "columnName": "role",
            "affinity": "TEXT",
            "notNull": false
          },
          {
            "fieldPath": "cachedAt",
            "columnName": "cachedAt",
            "affinity": "INTEGER",
            "notNull": true
          }
        ],
        "primaryKey": {
          "autoGenerate": false,
          "columnNames": [
            "id"
          ]
        },
        "indices": [],
        "foreignKeys": []
      },
      {
        "tableName": "cached_wallet_balance",
        "createSql": "CREATE TABLE IF NOT EXISTS `${TABLE_NAME}` (`id` TEXT NOT NULL, `balance` REAL NOT NULL, `currency` TEXT NOT NULL, `status` TEXT, `cachedAt` INTEGER NOT NULL, PRIMARY KEY(`id`))",
        "fields": [
          {
            "fieldPath": "id",
            "columnName": "id",
            "affinity": "TEXT",
            "notNull": true
          },
          {
            "fieldPath": "balance",
            "columnName": "balance",
            "affinity": "REAL",
            "notNull": true
          },
          {
            "fieldPath": "currency",
            "columnName": "currency",
            "affinity": "TEXT",
            "notNull": true
          },
          {
            "fieldPath": "status",
            "columnName": "status",
            "affinity": "TEXT",
            "notNull": false
          },
          {
            "fieldPath": "cachedAt",
            "columnName": "cachedAt",
            "affinity": "INTEGER",
            "notNull": true
          }
        ],
        "primaryKey": {
          "autoGenerate": false,
          "columnNames": [
            "id"
          ]
        },
        "indices": [],
        "foreignKeys": []
      },
      {
        "tableName": "cached_active_ride",
        "createSql": "CREATE TABLE IF NOT EXISTS `${TABLE_NAME}` (`id` TEXT NOT NULL, `rideStateJson` TEXT NOT NULL, `cachedAt` INTEGER NOT NULL, PRIMARY KEY(`id`))",
        "fields": [
          {
            "fieldPath": "id",
            "columnName": "id",
            "affinity": "TEXT",
            "notNull": true
          },
          {
            "fieldPath": "rideStateJson",
            "columnName": "rideStateJson",
            "affinity": "TEXT",
            "notNull": true
          },
          {
            "fieldPath": "cachedAt",
            "columnName": "cachedAt",
            "affinity": "INTEGER",
            "notNull": true
          }
        ],
        "primaryKey": {
          "autoGenerate": false,
          "columnNames": [
            "id"
          ]
        },
        "indices": [],
        "foreignKeys": []
      },
      {
        "tableName": "cached_saved_place",
        "createSql": "CREATE TABLE IF NOT EXISTS `${TABLE_NAME}` (`id` TEXT NOT NULL, `name` TEXT NOT NULL, `address` TEXT NOT NULL, `lat` REAL NOT NULL, `lng` REAL NOT NULL, `type` TEXT NOT NULL, `cachedAt` INTEGER NOT NULL, PRIMARY KEY(`id`))",
        "fields": [
          {
            "fieldPath": "id",
            "columnName": "id",
            "affinity": "TEXT",
            "notNull": true
          },
          {
            "fieldPath": "name",
            "columnName": "name",
            "affinity": "TEXT",
            "notNull": true
          },
          {
            "fieldPath": "address",
            "columnName": "address",
            "affinity": "TEXT",
            "notNull": true
          },
          {
            "fieldPath": "lat",
            "columnName": "lat",
            "affinity": "REAL",
            "notNull": true
          },
          {
            "fieldPath": "lng",
            "columnName": "lng",
            "affinity": "REAL",
            "notNull": true
          },
          {
            "fieldPath": "type",
            "columnName": "type",
            "affinity": "TEXT",
            "notNull": true
          },
          {
            "fieldPath": "cachedAt",
            "columnName": "cachedAt",
            "affinity": "INTEGER",
            "notNull": true
          }
        ],
        "primaryKey": {
          "autoGenerate": false,
          "columnNames": [
            "id"
          ]
        },
        "indices": [],
        "foreignKeys": []
      }
    ],
    "views": [],
    "setupQueries": [
      "CREATE TABLE IF NOT EXISTS room_master_table (id INTEGER PRIMARY KEY,identity_hash TEXT)",
      "INSERT OR REPLACE INTO room_master_table (id,identity_hash) VALUES(42, '593585992d558d718977027a4312716a')"
    ]
  }
}